CCD231/CCD231.srcs/sources_1/imports/SPI_AD5628/spi_base.v
//	Created@2021-01-26
//	Author: Youhua Xu
//


`timescale 1ns / 1ps

// SPI Master (不含MISO)
// NOTE:数据时钟频率是SCLK的一半，计数器一定要数清楚！
// TODO：进行规范化，改为每次发送固定长度的bit数（8位）
// Note added @2021-01-26: 作为“基模块”，还是设计成可以发送任意长度bits比较好，
// 这样一来在更高一层的模块中可以更加灵活地进行实例化。

module SPI_BASE
	#(
		parameter DATAWIDTH = 32,			// SPI数据宽度
        parameter CLKDIV    = 16			// 时钟分频倍率
	)
	(
    //  inputs:
		input                       clk,
		input                       rst,	// active high
		input wire[DATAWIDTH-1:0]   din,	// data to be send to slave-SPI devices
		input 						en,

		input						CPOL,
		input						CPHA,

    //  outputs:
		output                      sclk,
		output                      dout,	// MOSI
		output						finished	// 1 means finished transmission
	);

//	内部寄存器，可以改变状态
	reg			sclk_r;      // 分频时钟
	reg[7:0] 	clk_cnt;     // 分频时钟的计数器
    reg[7:0]    dat_cnt;     // 数据计数器（循环）
	reg[7:0]	d_cnt;		 // 数据的“位”指示器
	reg			dout_r;      // MOSI寄存器
	reg			cs_r,A0_r,A1_r;
	reg[7:0]	delay_cnt;
	reg			sclk_rdy;
	reg			finished_r;

//	将输出引脚信号连接到对应的内部寄存器
	assign dout     = dout_r;
	assign sclk     = sclk_r;
	assign finished = finished_r;

	localparam	DAT_CNT_MAX = 2*CLKDIV-1;

//	==================
//	处理数据的发送
	always@( posedge clk or posedge rst ) begin
		if(rst) begin
		//	根据时钟相位设置“数据准备”的时机
   			if( CPHA == 0)
				// dat_cnt <= 2*CLKDIV-1;
				dat_cnt <= DAT_CNT_MAX-1;
            else if( CPHA == 1 )
            	dat_cnt <= CLKDIV;

        	d_cnt        <= DATAWIDTH;
			finished_r   <= 1'b0;
		end
		else begin
			if(en == 1) begin
				// if( dat_cnt == 2*CLKDIV-1 ) begin
				if( dat_cnt == DAT_CNT_MAX ) begin
					dat_cnt <= 0;
					dout_r  <= din[d_cnt-1];
					d_cnt   <= d_cnt-1;

					if( d_cnt == 0 ) begin
						finished_r	<= 1'b1;
					end
				end
				else begin
					dat_cnt <= dat_cnt + 1;
				end

				// 注意：
				// 如果在这里进行判断，时钟周期会少1个，剩下31个时钟周期
				// if( d_cnt == 0 ) begin
				// 	cs_r		<= 1'b1;
				// 	finished	<= 1'b1;
				// end
			end
		end
	end

//	=================
//	分频时钟延时
	always @(posedge clk or posedge rst) begin
		if (rst) begin
			if( CPHA == 0 ) begin
				delay_cnt <= 0;
				sclk_rdy <= 1'b0;
			end
            else if( CPHA == 1 ) begin
            	delay_cnt <= CLKDIV;
            	sclk_rdy  <= 1'b1;
            end
		end
		else begin
			if( en==1 ) begin
				if(delay_cnt == CLKDIV)
					sclk_rdy <= 1'b1;
				else begin
					delay_cnt <= delay_cnt + 8'b1;
				end
			end
		end
	end

//	=================
//	分频时钟sclk
	always@( posedge clk or posedge rst ) begin
		if(rst) begin
		//	根据时钟极性设置空闲状态下的SCLK
			if( CPOL == 0 )
				sclk_r	<= 1'b0;
			else if( CPOL == 1)
				sclk_r  <= 1'b1;

		//	根据时钟相位设置时钟分频计数器初始值
			if( CPHA == 0 )
            	clk_cnt <= CLKDIV-1;
            else if( CPHA == 1 )
            	clk_cnt <= 0;
		end
		else begin
			if( en==1 ) begin
				if (sclk_rdy) begin
					if( clk_cnt == CLKDIV-1 ) begin
						sclk_r <= ~sclk_r;
						clk_cnt <= 8'b0;
					end
					else
						clk_cnt <= clk_cnt + 8'b1;
				end
			end
			else begin
		  //	根据时钟极性设置空闲状态下的SCLK
                if( CPOL == 0 )
                    sclk_r  <= 1'b0;
                else if( CPOL == 1)
                    sclk_r  <= 1'b1;
			end
		end
	end

endmodule

CCD231-debug-2021-01-26/CCD231-debug-2021-01-26.srcs/sources_1/imports/AD_Config_v2/spi4adc.v
`timescale 1ns / 1ps

module SPI4ADC(
//	inputs
	input				clk,
	input				rst,
	input wire[31:0] 	spi_data,
	input 				spi_cpol,
	input				spi_cpha,
	input				ps_A0,
	input				ps_A1,

//	outputs:
	output				A0,
	output				A1,
	output				sclk,
	output				mosi,
	output				status
	);

	assign A0 = ps_A0;
	assign A1 = ps_A1;

//  模拟一次RST脉冲，用于初始化SPI_BASE
	reg[7:0]  reset_cnt;
	reg       reset_r;
	reg		  en_r;

//	finished:连接SPI_BASE的finished
	wire finished;
	parameter clk_div = 5; // 如果输入时钟为50M，那么在spi_base内部分频的时钟为50M/5/2=5M

//	状态机：
	parameter SPI_IDLE		= 4'd0;
	parameter SPI_RESET	= 4'd1;
	parameter SPI_SEND		= 4'd2;
	parameter SPI_FINISHED	= 4'd3;
	reg[3:0] state;			// defailt: SPI_IDLE

//	SPI_BASE 例化
	SPI_BASE#(
			.DATAWIDTH(32),
            .CLKDIV(clk_div)
		) spi (
			.clk(clk),
			.rst(reset_r),
			.din(spi_data),
			.en(en_r),
			.CPOL(spi_cpol),
			.CPHA(spi_cpha),
			.sclk(sclk),
			.dout(mosi),
			.finished(finished)
		);

//	status 表示当前32bit是否传输完成
	reg status_r = 1'b0;
	assign status = status_r;

	always @(posedge clk or posedge rst) begin
		if ( rst ) begin
			// reset
			state			<= SPI_IDLE;
			en_r			<= 0;
			reset_r			<= 0;
			reset_cnt		<= 8'b0;
			status_r		<= 1'b0;			
		end
		else begin
			case(state)
				SPI_IDLE:
				begin
					if( status_r == 1'b0 ) begin
						state		<= SPI_RESET;
						en_r		<= 0;
	                    reset_r		<= 0;
	                    reset_cnt	<= 8'b0;
						status_r	<= 1'b0;
					end
				end

				SPI_RESET:
				begin
					if( reset_cnt <= 5 ) begin
						reset_r		<= 0;
						reset_cnt	<= reset_cnt + 1;
					end
					else if( reset_cnt <= 7 ) begin
						reset_r		<= 1;
						reset_cnt	<= reset_cnt + 1;
					end
					else if( reset_cnt >= 8 ) begin
						reset_r		<= 0;
						en_r		<= 1;
						state		<= SPI_SEND;
					end
				end

				SPI_SEND:
				begin
					if( finished == 1'b1 ) begin
						state	<= SPI_FINISHED;
						// disable SPI_BASE
						en_r	<= 0;
					end
				end

				SPI_FINISHED:
				begin
					state		<= SPI_IDLE;
					status_r	<= 1'b1;
				end

				default:
					state 	<= SPI_IDLE;
			endcase
		end
	end
endmodule

CCD231-20210215/CCD231-20210215.srcs/sim_1/imports/AD_Config_v2/tb.v
`timescale 1ns / 1ps

module test();

	//	inputs
	reg clk_50M;
	reg rst;
	reg[31:0] spi_data;
	reg spi_cpol;
	reg spi_cpha;
	reg ps_A0;
	reg ps_A1;

	// 	outputs
	wire A0, A1;
	wire sclk;
	wire mosi;
	wire status;

	// instalization of spi4adc

	SPI4ADC spi4adc(
		.clk(clk_50M),
		.rst(rst),
		.spi_data(spi_data),
		.spi_cpol(spi_cpol),
		.spi_cpha(spi_cpha),
		.ps_A0(ps_A0),
		.ps_A1(ps_A1),
		.A0(A0),
		.A1(A1),
		.sclk(sclk),
		.mosi(mosi),
		.status(status)
		);

	initial begin
		$dumpfile("wave.vcd");
		$dumpvars(0,test);
	end

	initial begin
		rst = 0;
		ps_A0 = 0;
		ps_A1 = 1;
		spi_cpol = 0;
		spi_cpha = 1;
		spi_data = 32'b1010_1010_1010_1010_1010_1010_1010_1010;

		#10 rst = ~rst;
		#5	rst = ~rst;

		// first round
		#9000;

		ps_A0 = 1;
		ps_A1 = 0;
		spi_cpol = 0;
		spi_cpha = 0;
		spi_data = 32'b0101_0101_0101_0101_0101_0101_0101_0101;

		#10 rst = ~rst;
		#5	rst = ~rst;

		// second round
		#7000;

		$finish;
	end

	// generate 50MHz system clock signal
	initial begin
		clk_50M = 0;
		forever # 10 clk_50M = ~clk_50M;
	end

endmodule

CCD231-20210215/CCD231-20210215.sim/sim_1/behav/xsim/wave.vcd
$date
   Sat Feb  6 16:21:42 2021
$end
$version
  2017.4
$end
$timescale
  1ps
$end
$scope module test $end
$var reg 1 ! clk_50M $end
$var reg 1 " rst $end
$var reg 32 # spi_data [31:0] $end
$var reg 1 $ spi_cpol $end
$var reg 1 % spi_cpha $end
$var reg 1 & ps_A0 $end
$var reg 1 ' ps_A1 $end
$var wire 1 ( A0 $end
$var wire 1 ) A1 $end
$var wire 1 * sclk $end
$var wire 1 + mosi $end
$var wire 1 , status $end
$scope module spi4adc $end
$var wire 1 - clk $end
$var wire 1 . rst $end
$var wire 32 / spi_data [31:0] $end
$var wire 1 0 spi_cpol $end
$var wire 1 1 spi_cpha $end
$var wire 1 2 ps_A0 $end
$var wire 1 3 ps_A1 $end
$var wire 1 ( A0 $end
$var wire 1 ) A1 $end
$var wire 1 * sclk $end
$var wire 1 + mosi $end
$var wire 1 , status $end
$var reg 8 4 reset_cnt [7:0] $end
$var reg 1 5 reset_r $end
$var reg 1 6 en_r $end
$var wire 1 7 finished $end
$var reg 4 8 state [3:0] $end
$var reg 1 9 status_r $end
$var parameter 32 : clk_div [31:0] $end
$var parameter 4 ; SPI_IDLE [3:0] $end
$var parameter 4 < SPI_RESET [3:0] $end
$var parameter 4 = SPI_SEND [3:0] $end
$var parameter 4 > SPI_FINISHED [3:0] $end
$scope module spi $end
$var wire 1 - clk $end
$var wire 1 ? rst $end
$var wire 32 / din [31:0] $end
$var wire 1 @ en $end
$var wire 1 0 CPOL $end
$var wire 1 1 CPHA $end
$var wire 1 * sclk $end
$var wire 1 + dout $end
$var wire 1 7 finished $end
$var reg 1 A sclk_r $end
$var reg 8 B clk_cnt [7:0] $end
$var reg 8 C dat_cnt [7:0] $end
$var reg 8 D d_cnt [7:0] $end
$var reg 1 E dout_r $end
$var reg 1 F cs_r $end
$var reg 1 G A0_r $end
$var reg 1 H A1_r $end
$var reg 8 I delay_cnt [7:0] $end
$var reg 1 J sclk_rdy $end
$var reg 1 K finished_r $end
$var parameter 32 L DATAWIDTH [31:0] $end
$var parameter 32 M CLKDIV [31:0] $end
$var parameter 32 N DAT_CNT_MAX [31:0] $end
$upscope $end
$upscope $end
$upscope $end
$enddefinitions $end
#0
$dumpvars
0!
0"
b10101010101010101010101010101010 #
0$
1%
0&
1'
0(
1)
x*
x+
0,
0-
0.
b10101010101010101010101010101010 /
00
11
02
13
bx 4
x5
x6
x7
bx 8
09
b101 :
b0 ;
b1 <
b10 =
b11 >
x?
x@
xA
bx B
bx C
bx D
xE
xF
xG
xH
bx I
xJ
xK
b100000 L
b101 M
b1001 N
$end
#10000
1!
1"
1-
1.
b0 4
05
06
b0 8
09
0?
0@
#15000
0"
0.
#20000
0!
0-
#30000
1!
1-
05
06
b1 8
09
#40000
0!
0-
#50000
1!
1-
b1 4
05
#60000
0!
0-
#70000
1!
1-
b10 4
05
#80000
0!
0-
#90000
1!
1-
b11 4
05
#100000
0!
0-
#110000
1!
1-
b100 4
05
#120000
0!
0-
#130000
1!
1-
b101 4
05
#140000
0!
0-
#150000
1!
1-
b110 4
05
#160000
0!
0-
#170000
1!
0*
1-
b111 4
15
07
1?
0A
b0 B
b101 C
b100000 D
b101 I
1J
0K
#180000
0!
0-
#190000
1!
1-
b1000 4
15
0A
0K
#200000
0!
0-
#210000
1!
1-
05
16
b10 8
0?
1@
0A
0K
#220000
0!
0-
#230000
1!
1-
b1 B
b110 C
#240000
0!
0-
#250000
1!
1-
b10 B
b111 C
#260000
0!
0-
#270000
1!
1-
b11 B
b1000 C
#280000
0!
0-
#290000
1!
1-
b100 B
b1001 C
#300000
0!
0-
#310000
1!
1*
1+
1-
1A
b0 B
b0 C
b11111 D
1E
#320000
0!
0-
#330000
1!
1-
b1 B
b1 C
#340000
0!
0-
#350000
1!
1-
b10 B
b10 C
#360000
0!
0-
#370000
1!
1-
b11 B
b11 C
#380000
0!
0-
#390000
1!
1-
b100 B
b100 C
#400000
0!
0-
#410000
1!
0*
1-
0A
b0 B
b101 C
#420000
0!
0-
#430000
1!
1-
b1 B
b110 C
#440000
0!
0-
#450000
1!
1-
b10 B
b111 C
#460000
0!
0-
#470000
1!
1-
b11 B
b1000 C
#480000
0!
0-
#490000
1!
1-
b100 B
b1001 C
#500000
0!
0-
#510000
1!
1*
0+
1-
1A
b0 B
b0 C
b11110 D
0E
#520000
0!
0-
#530000
1!
1-
b1 B
b1 C
#540000
0!
0-
#550000
1!
1-
b10 B
b10 C
#560000
0!
0-
#570000
1!
1-
b11 B
b11 C
#580000
0!
0-
#590000
1!
1-
b100 B
b100 C
#600000
0!
0-
#610000
1!
0*
1-
0A
b0 B
b101 C
#620000
0!
0-
#630000
1!
1-
b1 B
b110 C
#640000
0!
0-
#650000
1!
1-
b10 B
b111 C
#660000
0!
0-
#670000
1!
1-
b11 B
b1000 C
#680000
0!
0-
#690000
1!
1-
b100 B
b1001 C
#700000
0!
0-
#710000
1!
1*
1+
1-
1A
b0 B
b0 C
b11101 D
1E
#720000
0!
0-
#730000
1!
1-
b1 B
b1 C
#740000
0!
0-
#750000
1!
1-
b10 B
b10 C
#760000
0!
0-
#770000
1!
1-
b11 B
b11 C
#780000
0!
0-
#790000
1!
1-
b100 B
b100 C
#800000
0!
0-
#810000
1!
0*
1-
0A
b0 B
b101 C
#820000
0!
0-
#830000
1!
1-
b1 B
b110 C
#840000
0!
0-
#850000
1!
1-
b10 B
b111 C
#860000
0!
0-
#870000
1!
1-
b11 B
b1000 C
#880000
0!
0-
#890000
1!
1-
b100 B
b1001 C
#900000
0!
0-
#910000
1!
1*
0+
1-
1A
b0 B
b0 C
b11100 D
0E
#920000
0!
0-
#930000
1!
1-
b1 B
b1 C
#940000
0!
0-
#950000
1!
1-
b10 B
b10 C
#960000
0!
0-
#970000
1!
1-
b11 B
b11 C
#980000
0!
0-
#990000
1!
1-
b100 B
b100 C
#1000000
0!
0-
#1010000
1!
0*
1-
0A
b0 B
b101 C
#1020000
0!
0-
#1030000
1!
1-
b1 B
b110 C
#1040000
0!
0-
#1050000
1!
1-
b10 B
b111 C
#1060000
0!
0-
#1070000
1!
1-
b11 B
b1000 C
#1080000
0!
0-
#1090000
1!
1-
b100 B
b1001 C
#1100000
0!
0-
#1110000
1!
1*
1+
1-
1A
b0 B
b0 C
b11011 D
1E
#1120000
0!
0-
#1130000
1!
1-
b1 B
b1 C
#1140000
0!
0-
#1150000
1!
1-
b10 B
b10 C
#1160000
0!
0-
#1170000
1!
1-
b11 B
b11 C
#1180000
0!
0-
#1190000
1!
1-
b100 B
b100 C
#1200000
0!
0-
#1210000
1!
0*
1-
0A
b0 B
b101 C
#1220000
0!
0-
#1230000
1!
1-
b1 B
b110 C
#1240000
0!
0-
#1250000
1!
1-
b10 B
b111 C
#1260000
0!
0-
#1270000
1!
1-
b11 B
b1000 C
#1280000
0!
0-
#1290000
1!
1-
b100 B
b1001 C
#1300000
0!
0-
#1310000
1!
1*
0+
1-
1A
b0 B
b0 C
b11010 D
0E
#1320000
0!
0-
#1330000
1!
1-
b1 B
b1 C
#1340000
0!
0-
#1350000
1!
1-
b10 B
b10 C
#1360000
0!
0-
#1370000
1!
1-
b11 B
b11 C
#1380000
0!
0-
#1390000
1!
1-
b100 B
b100 C
#1400000
0!
0-
#1410000
1!
0*
1-
0A
b0 B
b101 C
#1420000
0!
0-
#1430000
1!
1-
b1 B
b110 C
#1440000
0!
0-
#1450000
1!
1-
b10 B
b111 C
#1460000
0!
0-
#1470000
1!
1-
b11 B
b1000 C
#1480000
0!
0-
#1490000
1!
1-
b100 B
b1001 C
#1500000
0!
0-
#1510000
1!
1*
1+
1-
1A
b0 B
b0 C
b11001 D
1E
#1520000
0!
0-
#1530000
1!
1-
b1 B
b1 C
#1540000
0!
0-
#1550000
1!
1-
b10 B
b10 C
#1560000
0!
0-
#1570000
1!
1-
b11 B
b11 C
#1580000
0!
0-
#1590000
1!
1-
b100 B
b100 C
#1600000
0!
0-
#1610000
1!
0*
1-
0A
b0 B
b101 C
#1620000
0!
0-
#1630000
1!
1-
b1 B
b110 C
#1640000
0!
0-
#1650000
1!
1-
b10 B
b111 C
#1660000
0!
0-
#1670000
1!
1-
b11 B
b1000 C
#1680000
0!
0-
#1690000
1!
1-
b100 B
b1001 C
#1700000
0!
0-
#1710000
1!
1*
0+
1-
1A
b0 B
b0 C
b11000 D
0E
#1720000
0!
0-
#1730000
1!
1-
b1 B
b1 C
#1740000
0!
0-
#1750000
1!
1-
b10 B
b10 C
#1760000
0!
0-
#1770000
1!
1-
b11 B
b11 C
#1780000
0!
0-
#1790000
1!
1-
b100 B
b100 C
#1800000
0!
0-
#1810000
1!
0*
1-
0A
b0 B
b101 C
#1820000
0!
0-
#1830000
1!
1-
b1 B
b110 C
#1840000
0!
0-
#1850000
1!
1-
b10 B
b111 C
#1860000
0!
0-
#1870000
1!
1-
b11 B
b1000 C
#1880000
0!
0-
#1890000
1!
1-
b100 B
b1001 C
#1900000
0!
0-
#1910000
1!
1*
1+
1-
1A
b0 B
b0 C
b10111 D
1E
#1920000
0!
0-
#1930000
1!
1-
b1 B
b1 C
#1940000
0!
0-
#1950000
1!
1-
b10 B
b10 C
#1960000
0!
0-
#1970000
1!
1-
b11 B
b11 C
#1980000
0!
0-
#1990000
1!
1-
b100 B
b100 C
#2000000
0!
0-
#2010000
1!
0*
1-
0A
b0 B
b101 C
#2020000
0!
0-
#2030000
1!
1-
b1 B
b110 C
#2040000
0!
0-
#2050000
1!
1-
b10 B
b111 C
#2060000
0!
0-
#2070000
1!
1-
b11 B
b1000 C
#2080000
0!
0-
#2090000
1!
1-
b100 B
b1001 C
#2100000
0!
0-
#2110000
1!
1*
0+
1-
1A
b0 B
b0 C
b10110 D
0E
#2120000
0!
0-
#2130000
1!
1-
b1 B
b1 C
#2140000
0!
0-
#2150000
1!
1-
b10 B
b10 C
#2160000
0!
0-
#2170000
1!
1-
b11 B
b11 C
#2180000
0!
0-
#2190000
1!
1-
b100 B
b100 C
#2200000
0!
0-
#2210000
1!
0*
1-
0A
b0 B
b101 C
#2220000
0!
0-
#2230000
1!
1-
b1 B
b110 C
#2240000
0!
0-
#2250000
1!
1-
b10 B
b111 C
#2260000
0!
0-
#2270000
1!
1-
b11 B
b1000 C
#2280000
0!
0-
#2290000
1!
1-
b100 B
b1001 C
#2300000
0!
0-
#2310000
1!
1*
1+
1-
1A
b0 B
b0 C
b10101 D
1E
#2320000
0!
0-
#2330000
1!
1-
b1 B
b1 C
#2340000
0!
0-
#2350000
1!
1-
b10 B
b10 C
#2360000
0!
0-
#2370000
1!
1-
b11 B
b11 C
#2380000
0!
0-
#2390000
1!
1-
b100 B
b100 C
#2400000
0!
0-
#2410000
1!
0*
1-
0A
b0 B
b101 C
#2420000
0!
0-
#2430000
1!
1-
b1 B
b110 C
#2440000
0!
0-
#2450000
1!
1-
b10 B
b111 C
#2460000
0!
0-
#2470000
1!
1-
b11 B
b1000 C
#2480000
0!
0-
#2490000
1!
1-
b100 B
b1001 C
#2500000
0!
0-
#2510000
1!
1*
0+
1-
1A
b0 B
b0 C
b10100 D
0E
#2520000
0!
0-
#2530000
1!
1-
b1 B
b1 C
#2540000
0!
0-
#2550000
1!
1-
b10 B
b10 C
#2560000
0!
0-
#2570000
1!
1-
b11 B
b11 C
#2580000
0!
0-
#2590000
1!
1-
b100 B
b100 C
#2600000
0!
0-
#2610000
1!
0*
1-
0A
b0 B
b101 C
#2620000
0!
0-
#2630000
1!
1-
b1 B
b110 C
#2640000
0!
0-
#2650000
1!
1-
b10 B
b111 C
#2660000
0!
0-
#2670000
1!
1-
b11 B
b1000 C
#2680000
0!
0-
#2690000
1!
1-
b100 B
b1001 C
#2700000
0!
0-
#2710000
1!
1*
1+
1-
1A
b0 B
b0 C
b10011 D
1E
#2720000
0!
0-
#2730000
1!
1-
b1 B
b1 C
#2740000
0!
0-
#2750000
1!
1-
b10 B
b10 C
#2760000
0!
0-
#2770000
1!
1-
b11 B
b11 C
#2780000
0!
0-
#2790000
1!
1-
b100 B
b100 C
#2800000
0!
0-
#2810000
1!
0*
1-
0A
b0 B
b101 C
#2820000
0!
0-
#2830000
1!
1-
b1 B
b110 C
#2840000
0!
0-
#2850000
1!
1-
b10 B
b111 C
#2860000
0!
0-
#2870000
1!
1-
b11 B
b1000 C
#2880000
0!
0-
#2890000
1!
1-
b100 B
b1001 C
#2900000
0!
0-
#2910000
1!
1*
0+
1-
1A
b0 B
b0 C
b10010 D
0E
#2920000
0!
0-
#2930000
1!
1-
b1 B
b1 C
#2940000
0!
0-
#2950000
1!
1-
b10 B
b10 C
#2960000
0!
0-
#2970000
1!
1-
b11 B
b11 C
#2980000
0!
0-
#2990000
1!
1-
b100 B
b100 C
#3000000
0!
0-
#3010000
1!
0*
1-
0A
b0 B
b101 C
#3020000
0!
0-
#3030000
1!
1-
b1 B
b110 C
#3040000
0!
0-
#3050000
1!
1-
b10 B
b111 C
#3060000
0!
0-
#3070000
1!
1-
b11 B
b1000 C
#3080000
0!
0-
#3090000
1!
1-
b100 B
b1001 C
#3100000
0!
0-
#3110000
1!
1*
1+
1-
1A
b0 B
b0 C
b10001 D
1E
#3120000
0!
0-
#3130000
1!
1-
b1 B
b1 C
#3140000
0!
0-
#3150000
1!
1-
b10 B
b10 C
#3160000
0!
0-
#3170000
1!
1-
b11 B
b11 C
#3180000
0!
0-
#3190000
1!
1-
b100 B
b100 C
#3200000
0!
0-
#3210000
1!
0*
1-
0A
b0 B
b101 C
#3220000
0!
0-
#3230000
1!
1-
b1 B
b110 C
#3240000
0!
0-
#3250000
1!
1-
b10 B
b111 C
#3260000
0!
0-
#3270000
1!
1-
b11 B
b1000 C
#3280000
0!
0-
#3290000
1!
1-
b100 B
b1001 C
#3300000
0!
0-
#3310000
1!
1*
0+
1-
1A
b0 B
b0 C
b10000 D
0E
#3320000
0!
0-
#3330000
1!
1-
b1 B
b1 C
#3340000
0!
0-
#3350000
1!
1-
b10 B
b10 C
#3360000
0!
0-
#3370000
1!
1-
b11 B
b11 C
#3380000
0!
0-
#3390000
1!
1-
b100 B
b100 C
#3400000
0!
0-
#3410000
1!
0*
1-
0A
b0 B
b101 C
#3420000
0!
0-
#3430000
1!
1-
b1 B
b110 C
#3440000
0!
0-
#3450000
1!
1-
b10 B
b111 C
#3460000
0!
0-
#3470000
1!
1-
b11 B
b1000 C
#3480000
0!
0-
#3490000
1!
1-
b100 B
b1001 C
#3500000
0!
0-
#3510000
1!
1*
1+
1-
1A
b0 B
b0 C
b1111 D
1E
#3520000
0!
0-
#3530000
1!
1-
b1 B
b1 C
#3540000
0!
0-
#3550000
1!
1-
b10 B
b10 C
#3560000
0!
0-
#3570000
1!
1-
b11 B
b11 C
#3580000
0!
0-
#3590000
1!
1-
b100 B
b100 C
#3600000
0!
0-
#3610000
1!
0*
1-
0A
b0 B
b101 C
#3620000
0!
0-
#3630000
1!
1-
b1 B
b110 C
#3640000
0!
0-
#3650000
1!
1-
b10 B
b111 C
#3660000
0!
0-
#3670000
1!
1-
b11 B
b1000 C
#3680000
0!
0-
#3690000
1!
1-
b100 B
b1001 C
#3700000
0!
0-
#3710000
1!
1*
0+
1-
1A
b0 B
b0 C
b1110 D
0E
#3720000
0!
0-
#3730000
1!
1-
b1 B
b1 C
#3740000
0!
0-
#3750000
1!
1-
b10 B
b10 C
#3760000
0!
0-
#3770000
1!
1-
b11 B
b11 C
#3780000
0!
0-
#3790000
1!
1-
b100 B
b100 C
#3800000
0!
0-
#3810000
1!
0*
1-
0A
b0 B
b101 C
#3820000
0!
0-
#3830000
1!
1-
b1 B
b110 C
#3840000
0!
0-
#3850000
1!
1-
b10 B
b111 C
#3860000
0!
0-
#3870000
1!
1-
b11 B
b1000 C
#3880000
0!
0-
#3890000
1!
1-
b100 B
b1001 C
#3900000
0!
0-
#3910000
1!
1*
1+
1-
1A
b0 B
b0 C
b1101 D
1E
#3920000
0!
0-
#3930000
1!
1-
b1 B
b1 C
#3940000
0!
0-
#3950000
1!
1-
b10 B
b10 C
#3960000
0!
0-
#3970000
1!
1-
b11 B
b11 C
#3980000
0!
0-
#3990000
1!
1-
b100 B
b100 C
#4000000
0!
0-
#4010000
1!
0*
1-
0A
b0 B
b101 C
#4020000
0!
0-
#4030000
1!
1-
b1 B
b110 C
#4040000
0!
0-
#4050000
1!
1-
b10 B
b111 C
#4060000
0!
0-
#4070000
1!
1-
b11 B
b1000 C
#4080000
0!
0-
#4090000
1!
1-
b100 B
b1001 C
#4100000
0!
0-
#4110000
1!
1*
0+
1-
1A
b0 B
b0 C
b1100 D
0E
#4120000
0!
0-
#4130000
1!
1-
b1 B
b1 C
#4140000
0!
0-
#4150000
1!
1-
b10 B
b10 C
#4160000
0!
0-
#4170000
1!
1-
b11 B
b11 C
#4180000
0!
0-
#4190000
1!
1-
b100 B
b100 C
#4200000
0!
0-
#4210000
1!
0*
1-
0A
b0 B
b101 C
#4220000
0!
0-
#4230000
1!
1-
b1 B
b110 C
#4240000
0!
0-
#4250000
1!
1-
b10 B
b111 C
#4260000
0!
0-
#4270000
1!
1-
b11 B
b1000 C
#4280000
0!
0-
#4290000
1!
1-
b100 B
b1001 C
#4300000
0!
0-
#4310000
1!
1*
1+
1-
1A
b0 B
b0 C
b1011 D
1E
#4320000
0!
0-
#4330000
1!
1-
b1 B
b1 C
#4340000
0!
0-
#4350000
1!
1-
b10 B
b10 C
#4360000
0!
0-
#4370000
1!
1-
b11 B
b11 C
#4380000
0!
0-
#4390000
1!
1-
b100 B
b100 C
#4400000
0!
0-
#4410000
1!
0*
1-
0A
b0 B
b101 C
#4420000
0!
0-
#4430000
1!
1-
b1 B
b110 C
#4440000
0!
0-
#4450000
1!
1-
b10 B
b111 C
#4460000
0!
0-
#4470000
1!
1-
b11 B
b1000 C
#4480000
0!
0-
#4490000
1!
1-
b100 B
b1001 C
#4500000
0!
0-
#4510000
1!
1*
0+
1-
1A
b0 B
b0 C
b1010 D
0E
#4520000
0!
0-
#4530000
1!
1-
b1 B
b1 C
#4540000
0!
0-
#4550000
1!
1-
b10 B
b10 C
#4560000
0!
0-
#4570000
1!
1-
b11 B
b11 C
#4580000
0!
0-
#4590000
1!
1-
b100 B
b100 C
#4600000
0!
0-
#4610000
1!
0*
1-
0A
b0 B
b101 C
#4620000
0!
0-
#4630000
1!
1-
b1 B
b110 C
#4640000
0!
0-
#4650000
1!
1-
b10 B
b111 C
#4660000
0!
0-
#4670000
1!
1-
b11 B
b1000 C
#4680000
0!
0-
#4690000
1!
1-
b100 B
b1001 C
#4700000
0!
0-
#4710000
1!
1*
1+
1-
1A
b0 B
b0 C
b1001 D
1E
#4720000
0!
0-
#4730000
1!
1-
b1 B
b1 C
#4740000
0!
0-
#4750000
1!
1-
b10 B
b10 C
#4760000
0!
0-
#4770000
1!
1-
b11 B
b11 C
#4780000
0!
0-
#4790000
1!
1-
b100 B
b100 C
#4800000
0!
0-
#4810000
1!
0*
1-
0A
b0 B
b101 C
#4820000
0!
0-
#4830000
1!
1-
b1 B
b110 C
#4840000
0!
0-
#4850000
1!
1-
b10 B
b111 C
#4860000
0!
0-
#4870000
1!
1-
b11 B
b1000 C
#4880000
0!
0-
#4890000
1!
1-
b100 B
b1001 C
#4900000
0!
0-
#4910000
1!
1*
0+
1-
1A
b0 B
b0 C
b1000 D
0E
#4920000
0!
0-
#4930000
1!
1-
b1 B
b1 C
#4940000
0!
0-
#4950000
1!
1-
b10 B
b10 C
#4960000
0!
0-
#4970000
1!
1-
b11 B
b11 C
#4980000
0!
0-
#4990000
1!
1-
b100 B
b100 C
#5000000
0!
0-
#5010000
1!
0*
1-
0A
b0 B
b101 C
#5020000
0!
0-
#5030000
1!
1-
b1 B
b110 C
#5040000
0!
0-
#5050000
1!
1-
b10 B
b111 C
#5060000
0!
0-
#5070000
1!
1-
b11 B
b1000 C
#5080000
0!
0-
#5090000
1!
1-
b100 B
b1001 C
#5100000
0!
0-
#5110000
1!
1*
1+
1-
1A
b0 B
b0 C
b111 D
1E
#5120000
0!
0-
#5130000
1!
1-
b1 B
b1 C
#5140000
0!
0-
#5150000
1!
1-
b10 B
b10 C
#5160000
0!
0-
#5170000
1!
1-
b11 B
b11 C
#5180000
0!
0-
#5190000
1!
1-
b100 B
b100 C
#5200000
0!
0-
#5210000
1!
0*
1-
0A
b0 B
b101 C
#5220000
0!
0-
#5230000
1!
1-
b1 B
b110 C
#5240000
0!
0-
#5250000
1!
1-
b10 B
b111 C
#5260000
0!
0-
#5270000
1!
1-
b11 B
b1000 C
#5280000
0!
0-
#5290000
1!
1-
b100 B
b1001 C
#5300000
0!
0-
#5310000
1!
1*
0+
1-
1A
b0 B
b0 C
b110 D
0E
#5320000
0!
0-
#5330000
1!
1-
b1 B
b1 C
#5340000
0!
0-
#5350000
1!
1-
b10 B
b10 C
#5360000
0!
0-
#5370000
1!
1-
b11 B
b11 C
#5380000
0!
0-
#5390000
1!
1-
b100 B
b100 C
#5400000
0!
0-
#5410000
1!
0*
1-
0A
b0 B
b101 C
#5420000
0!
0-
#5430000
1!
1-
b1 B
b110 C
#5440000
0!
0-
#5450000
1!
1-
b10 B
b111 C
#5460000
0!
0-
#5470000
1!
1-
b11 B
b1000 C
#5480000
0!
0-
#5490000
1!
1-
b100 B
b1001 C
#5500000
0!
0-
#5510000
1!
1*
1+
1-
1A
b0 B
b0 C
b101 D
1E
#5520000
0!
0-
#5530000
1!
1-
b1 B
b1 C
#5540000
0!
0-
#5550000
1!
1-
b10 B
b10 C
#5560000
0!
0-
#5570000
1!
1-
b11 B
b11 C
#5580000
0!
0-
#5590000
1!
1-
b100 B
b100 C
#5600000
0!
0-
#5610000
1!
0*
1-
0A
b0 B
b101 C
#5620000
0!
0-
#5630000
1!
1-
b1 B
b110 C
#5640000
0!
0-
#5650000
1!
1-
b10 B
b111 C
#5660000
0!
0-
#5670000
1!
1-
b11 B
b1000 C
